binaryconvert/__init__.py
binaryconvert/__main__.py
binaryconvert/cli.py
binaryconvert/convert.py
binaryconvert-3.0.0.dist-info/LICENSE
binaryconvert-3.0.0.dist-info/METADATA
binaryconvert-3.0.0.dist-info/WHEEL
binaryconvert-3.0.0.dist-info/entry_points.txt
binaryconvert-3.0.0.dist-info/top_level.txt
binaryconvert-3.0.0.dist-info/RECORD
