Metadata-Version: 2.1
Name: binaryconvert
Version: 3.0.0
Summary: A Python tool that converts text to binary and other formats like hexadecimal, Base64, Morse code, and more!
Home-page: https://github.com/wfxey/binaryconvert
Download-URL: https://github.com/wfxey/binaryconvert/archive/refs/tags/v3.0.0.tar.gz
Author: wfxey
Author-email: velis.help@web.de
License: MIT
Project-URL: Documentation, https://github.com/wfxey/binaryconvert#readme
Project-URL: Source, https://github.com/wfxey/binaryconvert
Project-URL: Bug Tracker, https://github.com/wfxey/binaryconvert/issues
Keywords: binary,binaries,text-to-binary,hexadecimal,base64,morse-code,utilities,converter
Classifier: Development Status :: 5 - Production/Stable
Classifier: Intended Audience :: Developers
Classifier: License :: OSI Approved :: MIT License
Classifier: Programming Language :: Python :: 3
Classifier: Programming Language :: Python :: 3.6
Classifier: Programming Language :: Python :: 3.7
Classifier: Programming Language :: Python :: 3.8
Classifier: Programming Language :: Python :: 3.9
Classifier: Programming Language :: Python :: 3.10
Classifier: Programming Language :: Python :: 3.11
Classifier: Topic :: Software Development :: Libraries
Classifier: Topic :: Utilities
Requires-Python: >=3.6
License-File: LICENSE
Provides-Extra: dev
Requires-Dist: pytest>=6.0.0; extra == "dev"
Requires-Dist: flake8>=4.0.0; extra == "dev"
